rustpy/__init__.py
rustpy/core/__init__.py
rustpy/core/borrow_checker.py
rustpy/core/lifetimes.py
rustpy/core/ownership.py
rustpy/core/references.py
rustpy/core/traits.py
rustpy/core/useless.py
rustpy/stdlib/__init__.py
rustpy/stdlib/collections.py
rustpy/stdlib/io.py
rustpy/stdlib/json.py
rustpy/stdlib/os.py
rustpy/stdlib/string.py
rustpy/stdlib/sys.py
rustpy/types/__init__.py
rustpy/types/option.py
rustpy/types/result.py
rustpy/types/string.py
rustpy/types/vec.py
rustpy_useless-0.1.1.dist-info/licenses/LICENSE
rustpy_useless-0.1.1.dist-info/METADATA
rustpy_useless-0.1.1.dist-info/WHEEL
rustpy_useless-0.1.1.dist-info/top_level.txt
rustpy_useless-0.1.1.dist-info/RECORD
