Metadata-Version: 2.4
Name: rustpy-useless
Version: 0.1.1
Summary: A Python library that parodies Rust syntax and concepts with intentionally bad optimization and excessive complexity. Every operation waits 1 second and executes 'pão com banana' before doing anything useful.
Author: Klee
Author-email: RustPY Team <porfavornaotenhoemail@gmail.com>
License: MIT
Project-URL: Homepage, https://github.com/kleeedolinux/rustpy
Project-URL: Documentation, https://github.com/kleeedolinux/rustpy#readme
Project-URL: Repository, https://github.com/kleeedolinux/rustpy
Project-URL: Issues, https://github.com/kleeedolinux/rustpy/issues
Keywords: rust,parody,useless,slow,borrow-checker,ownership,lifetimes,comedy
Classifier: Development Status :: 3 - Alpha
Classifier: Intended Audience :: Developers
Classifier: License :: OSI Approved :: MIT License
Classifier: Programming Language :: Python :: 3
Classifier: Programming Language :: Python :: 3.7
Classifier: Programming Language :: Python :: 3.8
Classifier: Programming Language :: Python :: 3.9
Classifier: Programming Language :: Python :: 3.10
Classifier: Programming Language :: Python :: 3.11
Classifier: Programming Language :: Python :: 3.12
Classifier: Topic :: Software Development :: Libraries :: Python Modules
Classifier: Topic :: Software Development :: Libraries
Classifier: Topic :: Utilities
Requires-Python: >=3.7
License-File: LICENSE
Dynamic: author
Dynamic: license-file
Dynamic: requires-python
